hytest/__init__.py
hytest/__main__.py
hytest/cfg.py
hytest/common.py
hytest/product.py
hytest/run.py
hytest/utils/__init__.py
hytest/utils/hytest.md
hytest/utils/icon.png
hytest/utils/log.py
hytest/utils/report.css
hytest/utils/report.js
hytest/utils/runner.py
hytest/utils/signal.py
hytest-0.9.5.dist-info/licenses/LICENSE.txt
hytest-0.9.5.dist-info/METADATA
hytest-0.9.5.dist-info/WHEEL
hytest-0.9.5.dist-info/entry_points.txt
hytest-0.9.5.dist-info/top_level.txt
hytest-0.9.5.dist-info/RECORD
