Metadata-Version: 2.4
Name: hytest
Version: 0.9.5
Summary: A generic automation framework for QA testing
Author-email: baiyueheiyu 白月黑羽 <jcyrss@gmail.com>
License-Expression: Apache-2.0
Project-URL: Homepage, https://github.com/jcyrss/hytest
Project-URL: Download, https://pypi.python.org/pypi/hytest
Keywords: hytest,automation,testautomation
Classifier: Development Status :: 4 - Beta
Classifier: Intended Audience :: Developers
Classifier: Topic :: Software Development :: Testing
Requires-Python: >=3.9
License-File: LICENSE.txt
Requires-Dist: rich
Requires-Dist: dominate
Requires-Dist: executing
Dynamic: license-file
